{
  "enhanced_analysis": {
    "Cat bowl": {
      "search_volume": 8100,
      "global_search_volume": 0,
      "search_volume_by_country": {},
      "monthly_searches": [
        {
          "year": 2025,
          "month": 12,
          "search_volume": 8100
        },
        {
          "year": 2025,
          "month": 11,
          "search_volume": 8100
        },
        {
          "year": 2025,
          "month": 10,
          "search_volume": 8100
        },
        {
          "year": 2025,
          "month": 9,
          "search_volume": 8100
        },
        {
          "year": 2025,
          "month": 8,
          "search_volume": 8100
        },
        {
          "year": 2025,
          "month": 7,
          "search_volume": 8100
        },
        {
          "year": 2025,
          "month": 6,
          "search_volume": 8100
        },
        {
          "year": 2025,
          "month": 5,
          "search_volume": 8100
        },
        {
          "year": 2025,
          "month": 4,
          "search_volume": 8100
        },
        {
          "year": 2025,
          "month": 3,
          "search_volume": 8100
        },
        {
          "year": 2025,
          "month": 2,
          "search_volume": 8100
        },
        {
          "year": 2025,
          "month": 1,
          "search_volume": 8100
        }
      ],
      "difficulty": "medium",
      "difficulty_score": 50.0,
      "competition": 0.0,
      "cpc": 0.96,
      "cpc_currency": null,
      "cps": null,
      "clicks": null,
      "trend_score": 0.0,
      "recommended": true,
      "reason": "Good search volume with manageable competition",
      "related_keywords": [
        "best Cat bowl",
        "top Cat bowl",
        "free Cat bowl",
        "online Cat bowl",
        "professional Cat bowl",
        "learn Cat bowl",
        "understand Cat bowl",
        "master Cat bowl"
      ],
      "related_keywords_enhanced": [],
      "long_tail_keywords": [
        "how to use Cat bowl",
        "what is Cat bowl",
        "why Cat bowl is important",
        "benefits of Cat bowl",
        "Cat bowl for beginners",
        "Cat bowl problems",
        "Cat bowl challenges"
      ],
      "questions": [],
      "topics": [],
      "keyword_ideas": [],
      "parent_topic": "Cat bowl",
      "category_type": "topic",
      "cluster_score": 0.5,
      "category": "Semantic Topics",
      "category_confidence": 0.5,
      "category_reasoning": "Semantically related topic cluster (difficulty: 50.0, volume: 8100)",
      "priority_score": 0.698,
      "ai_search_volume": 0,
      "ai_trend": 0.0,
      "ai_monthly_searches": [],
      "traffic_potential": null,
      "serp_features": [],
      "serp_feature_counts": {},
      "primary_intent": null,
      "intent_probabilities": {},
      "also_rank_for": [],
      "also_talk_about": [],
      "top_competitors": [],
      "first_seen": null,
      "last_updated": null
    },
    "cat bowls": {
      "search_volume": 0,
      "global_search_volume": 0,
      "search_volume_by_country": {},
      "monthly_searches": [],
      "difficulty": "medium",
      "difficulty_score": 50.0,
      "competition": 0.0,
      "cpc": 0.0,
      "cpc_currency": null,
      "cps": null,
      "clicks": null,
      "trend_score": 0.0,
      "recommended": false,
      "reason": "Low search volume - limited traffic potential",
      "related_keywords": [
        "best cat bowls",
        "top cat bowls",
        "free cat bowls",
        "online cat bowls",
        "professional cat bowls",
        "learn cat bowls",
        "understand cat bowls",
        "master cat bowls"
      ],
      "related_keywords_enhanced": [],
      "long_tail_keywords": [
        "how to use cat bowls",
        "what is cat bowls",
        "why cat bowls is important",
        "benefits of cat bowls",
        "cat bowls for beginners",
        "cat bowls problems",
        "cat bowls challenges"
      ],
      "questions": [],
      "topics": [],
      "keyword_ideas": [],
      "parent_topic": "cat bowls",
      "category_type": "topic",
      "cluster_score": 0.5,
      "category": "Semantic Topics",
      "category_confidence": 0.5,
      "category_reasoning": "Semantically related topic cluster (difficulty: 50.0, volume: 0)",
      "priority_score": 0.35,
      "ai_search_volume": 0,
      "ai_trend": 0.0,
      "ai_monthly_searches": [],
      "traffic_potential": null,
      "serp_features": [],
      "serp_feature_counts": {},
      "primary_intent": null,
      "intent_probabilities": {},
      "also_rank_for": [],
      "also_talk_about": [],
      "top_competitors": [],
      "first_seen": null,
      "last_updated": null
    },
    "cat bowl to slow eating": {
      "search_volume": 0,
      "global_search_volume": 0,
      "search_volume_by_country": {},
      "monthly_searches": [],
      "difficulty": "medium",
      "difficulty_score": 50.0,
      "competition": 0.0,
      "cpc": 0.0,
      "cpc_currency": null,
      "cps": null,
      "clicks": null,
      "trend_score": 0.0,
      "recommended": false,
      "reason": "Low search volume - limited traffic potential",
      "related_keywords": [
        "best cat bowl to slow eating",
        "top cat bowl to slow eating",
        "free cat bowl to slow eating",
        "online cat bowl to slow eating",
        "professional cat bowl to slow eating",
        "learn cat bowl to slow eating",
        "understand cat bowl to slow eating",
        "master cat bowl to slow eating"
      ],
      "related_keywords_enhanced": [],
      "long_tail_keywords": [
        "how to use cat bowl to slow eating",
        "what is cat bowl to slow eating",
        "why cat bowl to slow eating is important",
        "benefits of cat bowl to slow eating",
        "cat bowl to slow eating for beginners",
        "cat bowl to slow eating problems",
        "cat bowl to slow eating challenges"
      ],
      "questions": [],
      "topics": [],
      "keyword_ideas": [],
      "parent_topic": "cat bowl to slow eating",
      "category_type": "topic",
      "cluster_score": 0.5,
      "category": "Semantic Topics",
      "category_confidence": 0.5,
      "category_reasoning": "Semantically related topic cluster (difficulty: 50.0, volume: 0)",
      "priority_score": 0.35,
      "ai_search_volume": 0,
      "ai_trend": 0.0,
      "ai_monthly_searches": [],
      "traffic_potential": null,
      "serp_features": [],
      "serp_feature_counts": {},
      "primary_intent": null,
      "intent_probabilities": {},
      "also_rank_for": [],
      "also_talk_about": [],
      "top_competitors": [],
      "first_seen": null,
      "last_updated": null
    },
    "cat bowls elevated": {
      "search_volume": 0,
      "global_search_volume": 0,
      "search_volume_by_country": {},
      "monthly_searches": [],
      "difficulty": "medium",
      "difficulty_score": 50.0,
      "competition": 0.0,
      "cpc": 0.0,
      "cpc_currency": null,
      "cps": null,
      "clicks": null,
      "trend_score": 0.0,
      "recommended": false,
      "reason": "Low search volume - limited traffic potential",
      "related_keywords": [
        "best cat bowls elevated",
        "top cat bowls elevated",
        "free cat bowls elevated",
        "online cat bowls elevated",
        "professional cat bowls elevated",
        "learn cat bowls elevated",
        "understand cat bowls elevated",
        "master cat bowls elevated"
      ],
      "related_keywords_enhanced": [],
      "long_tail_keywords": [
        "how to use cat bowls elevated",
        "what is cat bowls elevated",
        "why cat bowls elevated is important",
        "benefits of cat bowls elevated",
        "cat bowls elevated for beginners",
        "cat bowls elevated problems",
        "cat bowls elevated challenges"
      ],
      "questions": [],
      "topics": [],
      "keyword_ideas": [],
      "parent_topic": "cat bowls elevated",
      "category_type": "topic",
      "cluster_score": 0.5,
      "category": "Semantic Topics",
      "category_confidence": 0.5,
      "category_reasoning": "Semantically related topic cluster (difficulty: 50.0, volume: 0)",
      "priority_score": 0.35,
      "ai_search_volume": 0,
      "ai_trend": 0.0,
      "ai_monthly_searches": [],
      "traffic_potential": null,
      "serp_features": [],
      "serp_feature_counts": {},
      "primary_intent": null,
      "intent_probabilities": {},
      "also_rank_for": [],
      "also_talk_about": [],
      "top_competitors": [],
      "first_seen": null,
      "last_updated": null
    },
    "cat bowl ceramic": {
      "search_volume": 0,
      "global_search_volume": 0,
      "search_volume_by_country": {},
      "monthly_searches": [],
      "difficulty": "medium",
      "difficulty_score": 50.0,
      "competition": 0.0,
      "cpc": 0.0,
      "cpc_currency": null,
      "cps": null,
      "clicks": null,
      "trend_score": 0.0,
      "recommended": false,
      "reason": "Low search volume - limited traffic potential",
      "related_keywords": [
        "best cat bowl ceramic",
        "top cat bowl ceramic",
        "free cat bowl ceramic",
        "online cat bowl ceramic",
        "professional cat bowl ceramic",
        "learn cat bowl ceramic",
        "understand cat bowl ceramic",
        "master cat bowl ceramic"
      ],
      "related_keywords_enhanced": [],
      "long_tail_keywords": [
        "how to use cat bowl ceramic",
        "what is cat bowl ceramic",
        "why cat bowl ceramic is important",
        "benefits of cat bowl ceramic",
        "cat bowl ceramic for beginners",
        "cat bowl ceramic problems",
        "cat bowl ceramic challenges"
      ],
      "questions": [],
      "topics": [],
      "keyword_ideas": [],
      "parent_topic": "cat bowl ceramic",
      "category_type": "topic",
      "cluster_score": 0.5,
      "category": "Semantic Topics",
      "category_confidence": 0.5,
      "category_reasoning": "Semantically related topic cluster (difficulty: 50.0, volume: 0)",
      "priority_score": 0.35,
      "ai_search_volume": 0,
      "ai_trend": 0.0,
      "ai_monthly_searches": [],
      "traffic_potential": null,
      "serp_features": [],
      "serp_feature_counts": {},
      "primary_intent": null,
      "intent_probabilities": {},
      "also_rank_for": [],
      "also_talk_about": [],
      "top_competitors": [],
      "first_seen": null,
      "last_updated": null
    },
    "cat bowl stand": {
      "search_volume": 0,
      "global_search_volume": 0,
      "search_volume_by_country": {},
      "monthly_searches": [],
      "difficulty": "medium",
      "difficulty_score": 50.0,
      "competition": 0.0,
      "cpc": 0.0,
      "cpc_currency": null,
      "cps": null,
      "clicks": null,
      "trend_score": 0.0,
      "recommended": false,
      "reason": "Low search volume - limited traffic potential",
      "related_keywords": [
        "best cat bowl stand",
        "top cat bowl stand",
        "free cat bowl stand",
        "online cat bowl stand",
        "professional cat bowl stand",
        "learn cat bowl stand",
        "understand cat bowl stand",
        "master cat bowl stand"
      ],
      "related_keywords_enhanced": [],
      "long_tail_keywords": [
        "how to use cat bowl stand",
        "what is cat bowl stand",
        "why cat bowl stand is important",
        "benefits of cat bowl stand",
        "cat bowl stand for beginners",
        "cat bowl stand problems",
        "cat bowl stand challenges"
      ],
      "questions": [],
      "topics": [],
      "keyword_ideas": [],
      "parent_topic": "cat bowl stand",
      "category_type": "topic",
      "cluster_score": 0.5,
      "category": "Semantic Topics",
      "category_confidence": 0.5,
      "category_reasoning": "Semantically related topic cluster (difficulty: 50.0, volume: 0)",
      "priority_score": 0.35,
      "ai_search_volume": 0,
      "ai_trend": 0.0,
      "ai_monthly_searches": [],
      "traffic_potential": null,
      "serp_features": [],
      "serp_feature_counts": {},
      "primary_intent": null,
      "intent_probabilities": {},
      "also_rank_for": [],
      "also_talk_about": [],
      "top_competitors": [],
      "first_seen": null,
      "last_updated": null
    },
    "cat bowling game": {
      "search_volume": 0,
      "global_search_volume": 0,
      "search_volume_by_country": {},
      "monthly_searches": [],
      "difficulty": "medium",
      "difficulty_score": 50.0,
      "competition": 0.0,
      "cpc": 0.0,
      "cpc_currency": null,
      "cps": null,
      "clicks": null,
      "trend_score": 0.0,
      "recommended": false,
      "reason": "Low search volume - limited traffic potential",
      "related_keywords": [
        "best cat bowling game",
        "top cat bowling game",
        "free cat bowling game",
        "online cat bowling game",
        "professional cat bowling game",
        "learn cat bowling game",
        "understand cat bowling game",
        "master cat bowling game"
      ],
      "related_keywords_enhanced": [],
      "long_tail_keywords": [
        "how to use cat bowling game",
        "what is cat bowling game",
        "why cat bowling game is important",
        "benefits of cat bowling game",
        "cat bowling game for beginners",
        "cat bowling game problems",
        "cat bowling game challenges"
      ],
      "questions": [],
      "topics": [],
      "keyword_ideas": [],
      "parent_topic": "cat bowling game",
      "category_type": "topic",
      "cluster_score": 0.5,
      "category": "Semantic Topics",
      "category_confidence": 0.5,
      "category_reasoning": "Semantically related topic cluster (difficulty: 50.0, volume: 0)",
      "priority_score": 0.35,
      "ai_search_volume": 0,
      "ai_trend": 0.0,
      "ai_monthly_searches": [],
      "traffic_potential": null,
      "serp_features": [],
      "serp_feature_counts": {},
      "primary_intent": null,
      "intent_probabilities": {},
      "also_rank_for": [],
      "also_talk_about": [],
      "top_competitors": [],
      "first_seen": null,
      "last_updated": null
    },
    "cat bowl with lid": {
      "search_volume": 0,
      "global_search_volume": 0,
      "search_volume_by_country": {},
      "monthly_searches": [],
      "difficulty": "medium",
      "difficulty_score": 50.0,
      "competition": 0.0,
      "cpc": 0.0,
      "cpc_currency": null,
      "cps": null,
      "clicks": null,
      "trend_score": 0.0,
      "recommended": false,
      "reason": "Low search volume - limited traffic potential",
      "related_keywords": [
        "best cat bowl with lid",
        "top cat bowl with lid",
        "free cat bowl with lid",
        "online cat bowl with lid",
        "professional cat bowl with lid",
        "learn cat bowl with lid",
        "understand cat bowl with lid",
        "master cat bowl with lid"
      ],
      "related_keywords_enhanced": [],
      "long_tail_keywords": [
        "how to use cat bowl with lid",
        "what is cat bowl with lid",
        "why cat bowl with lid is important",
        "benefits of cat bowl with lid",
        "cat bowl with lid for beginners",
        "cat bowl with lid problems",
        "cat bowl with lid challenges"
      ],
      "questions": [],
      "topics": [],
      "keyword_ideas": [],
      "parent_topic": "cat bowl with lid",
      "category_type": "topic",
      "cluster_score": 0.5,
      "category": "Semantic Topics",
      "category_confidence": 0.5,
      "category_reasoning": "Semantically related topic cluster (difficulty: 50.0, volume: 0)",
      "priority_score": 0.35,
      "ai_search_volume": 0,
      "ai_trend": 0.0,
      "ai_monthly_searches": [],
      "traffic_potential": null,
      "serp_features": [],
      "serp_feature_counts": {},
      "primary_intent": null,
      "intent_probabilities": {},
      "also_rank_for": [],
      "also_talk_about": [],
      "top_competitors": [],
      "first_seen": null,
      "last_updated": null
    },
    "cat bowl mat": {
      "search_volume": 0,
      "global_search_volume": 0,
      "search_volume_by_country": {},
      "monthly_searches": [],
      "difficulty": "medium",
      "difficulty_score": 50.0,
      "competition": 0.0,
      "cpc": 0.0,
      "cpc_currency": null,
      "cps": null,
      "clicks": null,
      "trend_score": 0.0,
      "recommended": false,
      "reason": "Low search volume - limited traffic potential",
      "related_keywords": [
        "best cat bowl mat",
        "top cat bowl mat",
        "free cat bowl mat",
        "online cat bowl mat",
        "professional cat bowl mat",
        "learn cat bowl mat",
        "understand cat bowl mat",
        "master cat bowl mat"
      ],
      "related_keywords_enhanced": [],
      "long_tail_keywords": [
        "how to use cat bowl mat",
        "what is cat bowl mat",
        "why cat bowl mat is important",
        "benefits of cat bowl mat",
        "cat bowl mat for beginners",
        "cat bowl mat problems",
        "cat bowl mat challenges"
      ],
      "questions": [],
      "topics": [],
      "keyword_ideas": [],
      "parent_topic": "cat bowl mat",
      "category_type": "topic",
      "cluster_score": 0.5,
      "category": "Semantic Topics",
      "category_confidence": 0.5,
      "category_reasoning": "Semantically related topic cluster (difficulty: 50.0, volume: 0)",
      "priority_score": 0.35,
      "ai_search_volume": 0,
      "ai_trend": 0.0,
      "ai_monthly_searches": [],
      "traffic_potential": null,
      "serp_features": [],
      "serp_feature_counts": {},
      "primary_intent": null,
      "intent_probabilities": {},
      "also_rank_for": [],
      "also_talk_about": [],
      "top_competitors": [],
      "first_seen": null,
      "last_updated": null
    },
    "cat bowl set": {
      "search_volume": 0,
      "global_search_volume": 0,
      "search_volume_by_country": {},
      "monthly_searches": [],
      "difficulty": "medium",
      "difficulty_score": 50.0,
      "competition": 0.0,
      "cpc": 0.0,
      "cpc_currency": null,
      "cps": null,
      "clicks": null,
      "trend_score": 0.0,
      "recommended": false,
      "reason": "Low search volume - limited traffic potential",
      "related_keywords": [
        "best cat bowl set",
        "top cat bowl set",
        "free cat bowl set",
        "online cat bowl set",
        "professional cat bowl set",
        "learn cat bowl set",
        "understand cat bowl set",
        "master cat bowl set"
      ],
      "related_keywords_enhanced": [],
      "long_tail_keywords": [
        "how to use cat bowl set",
        "what is cat bowl set",
        "why cat bowl set is important",
        "benefits of cat bowl set",
        "cat bowl set for beginners",
        "cat bowl set problems",
        "cat bowl set challenges"
      ],
      "questions": [],
      "topics": [],
      "keyword_ideas": [],
      "parent_topic": "cat bowl set",
      "category_type": "topic",
      "cluster_score": 0.5,
      "category": "Semantic Topics",
      "category_confidence": 0.5,
      "category_reasoning": "Semantically related topic cluster (difficulty: 50.0, volume: 0)",
      "priority_score": 0.35,
      "ai_search_volume": 0,
      "ai_trend": 0.0,
      "ai_monthly_searches": [],
      "traffic_potential": null,
      "serp_features": [],
      "serp_feature_counts": {},
      "primary_intent": null,
      "intent_probabilities": {},
      "also_rank_for": [],
      "also_talk_about": [],
      "top_competitors": [],
      "first_seen": null,
      "last_updated": null
    },
    "cat bowl bed": {
      "search_volume": 0,
      "global_search_volume": 0,
      "search_volume_by_country": {},
      "monthly_searches": [],
      "difficulty": "medium",
      "difficulty_score": 50.0,
      "competition": 0.0,
      "cpc": 0.0,
      "cpc_currency": null,
      "cps": null,
      "clicks": null,
      "trend_score": 0.0,
      "recommended": false,
      "reason": "Low search volume - limited traffic potential",
      "related_keywords": [
        "best cat bowl bed",
        "top cat bowl bed",
        "free cat bowl bed",
        "online cat bowl bed",
        "professional cat bowl bed",
        "learn cat bowl bed",
        "understand cat bowl bed",
        "master cat bowl bed"
      ],
      "related_keywords_enhanced": [],
      "long_tail_keywords": [
        "how to use cat bowl bed",
        "what is cat bowl bed",
        "why cat bowl bed is important",
        "benefits of cat bowl bed",
        "cat bowl bed for beginners",
        "cat bowl bed problems",
        "cat bowl bed challenges"
      ],
      "questions": [],
      "topics": [],
      "keyword_ideas": [],
      "parent_topic": "cat bowl bed",
      "category_type": "topic",
      "cluster_score": 0.5,
      "category": "Semantic Topics",
      "category_confidence": 0.5,
      "category_reasoning": "Semantically related topic cluster (difficulty: 50.0, volume: 0)",
      "priority_score": 0.35,
      "ai_search_volume": 0,
      "ai_trend": 0.0,
      "ai_monthly_searches": [],
      "traffic_potential": null,
      "serp_features": [],
      "serp_feature_counts": {},
      "primary_intent": null,
      "intent_probabilities": {},
      "also_rank_for": [],
      "also_talk_about": [],
      "top_competitors": [],
      "first_seen": null,
      "last_updated": null
    },
    "cat bowls near me": {
      "search_volume": 0,
      "global_search_volume": 0,
      "search_volume_by_country": {},
      "monthly_searches": [],
      "difficulty": "medium",
      "difficulty_score": 50.0,
      "competition": 0.0,
      "cpc": 0.0,
      "cpc_currency": null,
      "cps": null,
      "clicks": null,
      "trend_score": 0.0,
      "recommended": false,
      "reason": "Low search volume - limited traffic potential",
      "related_keywords": [
        "best cat bowls near me",
        "top cat bowls near me",
        "free cat bowls near me",
        "online cat bowls near me",
        "professional cat bowls near me",
        "learn cat bowls near me",
        "understand cat bowls near me",
        "master cat bowls near me"
      ],
      "related_keywords_enhanced": [],
      "long_tail_keywords": [
        "how to use cat bowls near me",
        "what is cat bowls near me",
        "why cat bowls near me is important",
        "benefits of cat bowls near me",
        "cat bowls near me for beginners",
        "cat bowls near me problems",
        "cat bowls near me challenges"
      ],
      "questions": [],
      "topics": [],
      "keyword_ideas": [],
      "parent_topic": "cat bowls near me",
      "category_type": "topic",
      "cluster_score": 0.5,
      "category": "Semantic Topics",
      "category_confidence": 0.5,
      "category_reasoning": "Semantically related topic cluster (difficulty: 50.0, volume: 0)",
      "priority_score": 0.35,
      "ai_search_volume": 0,
      "ai_trend": 0.0,
      "ai_monthly_searches": [],
      "traffic_potential": null,
      "serp_features": [],
      "serp_feature_counts": {},
      "primary_intent": null,
      "intent_probabilities": {},
      "also_rank_for": [],
      "also_talk_about": [],
      "top_competitors": [],
      "first_seen": null,
      "last_updated": null
    },
    "cat bowling ball": {
      "search_volume": 0,
      "global_search_volume": 0,
      "search_volume_by_country": {},
      "monthly_searches": [],
      "difficulty": "medium",
      "difficulty_score": 50.0,
      "competition": 0.0,
      "cpc": 0.0,
      "cpc_currency": null,
      "cps": null,
      "clicks": null,
      "trend_score": 0.0,
      "recommended": false,
      "reason": "Low search volume - limited traffic potential",
      "related_keywords": [
        "best cat bowling ball",
        "top cat bowling ball",
        "free cat bowling ball",
        "online cat bowling ball",
        "professional cat bowling ball",
        "learn cat bowling ball",
        "understand cat bowling ball",
        "master cat bowling ball"
      ],
      "related_keywords_enhanced": [],
      "long_tail_keywords": [
        "how to use cat bowling ball",
        "what is cat bowling ball",
        "why cat bowling ball is important",
        "benefits of cat bowling ball",
        "cat bowling ball for beginners",
        "cat bowling ball problems",
        "cat bowling ball challenges"
      ],
      "questions": [],
      "topics": [],
      "keyword_ideas": [],
      "parent_topic": "cat bowling ball",
      "category_type": "topic",
      "cluster_score": 0.5,
      "category": "Semantic Topics",
      "category_confidence": 0.5,
      "category_reasoning": "Semantically related topic cluster (difficulty: 50.0, volume: 0)",
      "priority_score": 0.35,
      "ai_search_volume": 0,
      "ai_trend": 0.0,
      "ai_monthly_searches": [],
      "traffic_potential": null,
      "serp_features": [],
      "serp_feature_counts": {},
      "primary_intent": null,
      "intent_probabilities": {},
      "also_rank_for": [],
      "also_talk_about": [],
      "top_competitors": [],
      "first_seen": null,
      "last_updated": null
    },
    "cat bowls walmart": {
      "search_volume": 0,
      "global_search_volume": 0,
      "search_volume_by_country": {},
      "monthly_searches": [],
      "difficulty": "medium",
      "difficulty_score": 50.0,
      "competition": 0.0,
      "cpc": 0.0,
      "cpc_currency": null,
      "cps": null,
      "clicks": null,
      "trend_score": 0.0,
      "recommended": false,
      "reason": "Low search volume - limited traffic potential",
      "related_keywords": [
        "best cat bowls walmart",
        "top cat bowls walmart",
        "free cat bowls walmart",
        "online cat bowls walmart",
        "professional cat bowls walmart",
        "learn cat bowls walmart",
        "understand cat bowls walmart",
        "master cat bowls walmart"
      ],
      "related_keywords_enhanced": [],
      "long_tail_keywords": [
        "how to use cat bowls walmart",
        "what is cat bowls walmart",
        "why cat bowls walmart is important",
        "benefits of cat bowls walmart",
        "cat bowls walmart for beginners",
        "cat bowls walmart problems",
        "cat bowls walmart challenges"
      ],
      "questions": [],
      "topics": [],
      "keyword_ideas": [],
      "parent_topic": "cat bowls walmart",
      "category_type": "topic",
      "cluster_score": 0.5,
      "category": "Semantic Topics",
      "category_confidence": 0.5,
      "category_reasoning": "Semantically related topic cluster (difficulty: 50.0, volume: 0)",
      "priority_score": 0.35,
      "ai_search_volume": 0,
      "ai_trend": 0.0,
      "ai_monthly_searches": [],
      "traffic_potential": null,
      "serp_features": [],
      "serp_feature_counts": {},
      "primary_intent": null,
      "intent_probabilities": {},
      "also_rank_for": [],
      "also_talk_about": [],
      "top_competitors": [],
      "first_seen": null,
      "last_updated": null
    }
  },
  "total_keywords": 14,
  "original_keywords": [
    "Cat bowl"
  ],
  "suggested_keywords": [
    "cat bowls",
    "cat bowl to slow eating",
    "cat bowls elevated",
    "cat bowl ceramic",
    "cat bowl stand",
    "cat bowling game",
    "cat bowl with lid",
    "cat bowl mat",
    "cat bowl set",
    "cat bowl bed",
    "cat bowls near me",
    "cat bowling ball",
    "cat bowls walmart"
  ],
  "clusters": [
    {
      "parent_topic": "Cat bowl",
      "keywords": [
        "Cat bowl"
      ],
      "cluster_score": 0.5,
      "category_type": "topic",
      "keyword_count": 1,
      "category": "Semantic Topics",
      "priority": 4,
      "content_recommendations": {
        "pillar_title": "Complete Guide to Cat bowl",
        "pillar_description": "Comprehensive guide to cat bowl. Learn everything about cat bowl including best practices, expert tips, and actionable strategies.",
        "pillar_url": "/complete-guide-to-cat-bowl",
        "sub_pages": [],
        "estimated_word_count": 1980
      }
    },
    {
      "parent_topic": "cat bowls",
      "keywords": [
        "cat bowls"
      ],
      "cluster_score": 0.5,
      "category_type": "topic",
      "keyword_count": 1,
      "category": "Semantic Topics",
      "priority": 2,
      "content_recommendations": {
        "pillar_title": "Complete Guide to cat bowls",
        "pillar_description": "Comprehensive guide to cat bowls. Learn everything about cat bowls including best practices, expert tips, and actionable strategies.",
        "pillar_url": "/complete-guide-to-cat-bowls",
        "sub_pages": [],
        "estimated_word_count": 1980
      }
    },
    {
      "parent_topic": "cat bowl to slow eating",
      "keywords": [
        "cat bowl to slow eating"
      ],
      "cluster_score": 0.5,
      "category_type": "topic",
      "keyword_count": 1,
      "category": "Semantic Topics",
      "priority": 2,
      "content_recommendations": {
        "pillar_title": "Complete Guide to cat bowl to slow eating",
        "pillar_description": "Comprehensive guide to cat bowl to slow eating. Learn everything about cat bowl to slow eating including best practices, expert tips, and actionable strategies.",
        "pillar_url": "/complete-guide-to-cat-bowl-to-slow-eating",
        "sub_pages": [],
        "estimated_word_count": 1980
      }
    },
    {
      "parent_topic": "cat bowls elevated",
      "keywords": [
        "cat bowls elevated"
      ],
      "cluster_score": 0.5,
      "category_type": "topic",
      "keyword_count": 1,
      "category": "Semantic Topics",
      "priority": 2,
      "content_recommendations": {
        "pillar_title": "Complete Guide to cat bowls elevated",
        "pillar_description": "Comprehensive guide to cat bowls elevated. Learn everything about cat bowls elevated including best practices, expert tips, and actionable strategies.",
        "pillar_url": "/complete-guide-to-cat-bowls-elevated",
        "sub_pages": [],
        "estimated_word_count": 1980
      }
    },
    {
      "parent_topic": "cat bowl ceramic",
      "keywords": [
        "cat bowl ceramic"
      ],
      "cluster_score": 0.5,
      "category_type": "topic",
      "keyword_count": 1,
      "category": "Semantic Topics",
      "priority": 2,
      "content_recommendations": {
        "pillar_title": "Complete Guide to cat bowl ceramic",
        "pillar_description": "Comprehensive guide to cat bowl ceramic. Learn everything about cat bowl ceramic including best practices, expert tips, and actionable strategies.",
        "pillar_url": "/complete-guide-to-cat-bowl-ceramic",
        "sub_pages": [],
        "estimated_word_count": 1980
      }
    },
    {
      "parent_topic": "cat bowl stand",
      "keywords": [
        "cat bowl stand"
      ],
      "cluster_score": 0.5,
      "category_type": "topic",
      "keyword_count": 1,
      "category": "Semantic Topics",
      "priority": 2,
      "content_recommendations": {
        "pillar_title": "Complete Guide to cat bowl stand",
        "pillar_description": "Comprehensive guide to cat bowl stand. Learn everything about cat bowl stand including best practices, expert tips, and actionable strategies.",
        "pillar_url": "/complete-guide-to-cat-bowl-stand",
        "sub_pages": [],
        "estimated_word_count": 1980
      }
    },
    {
      "parent_topic": "cat bowling game",
      "keywords": [
        "cat bowling game"
      ],
      "cluster_score": 0.5,
      "category_type": "topic",
      "keyword_count": 1,
      "category": "Semantic Topics",
      "priority": 2,
      "content_recommendations": {
        "pillar_title": "Complete Guide to cat bowling game",
        "pillar_description": "Comprehensive guide to cat bowling game. Learn everything about cat bowling game including best practices, expert tips, and actionable strategies.",
        "pillar_url": "/complete-guide-to-cat-bowling-game",
        "sub_pages": [],
        "estimated_word_count": 1980
      }
    },
    {
      "parent_topic": "cat bowl with lid",
      "keywords": [
        "cat bowl with lid"
      ],
      "cluster_score": 0.5,
      "category_type": "topic",
      "keyword_count": 1,
      "category": "Semantic Topics",
      "priority": 2,
      "content_recommendations": {
        "pillar_title": "Complete Guide to cat bowl with lid",
        "pillar_description": "Comprehensive guide to cat bowl with lid. Learn everything about cat bowl with lid including best practices, expert tips, and actionable strategies.",
        "pillar_url": "/complete-guide-to-cat-bowl-with-lid",
        "sub_pages": [],
        "estimated_word_count": 1980
      }
    },
    {
      "parent_topic": "cat bowl mat",
      "keywords": [
        "cat bowl mat"
      ],
      "cluster_score": 0.5,
      "category_type": "topic",
      "keyword_count": 1,
      "category": "Semantic Topics",
      "priority": 2,
      "content_recommendations": {
        "pillar_title": "Complete Guide to cat bowl mat",
        "pillar_description": "Comprehensive guide to cat bowl mat. Learn everything about cat bowl mat including best practices, expert tips, and actionable strategies.",
        "pillar_url": "/complete-guide-to-cat-bowl-mat",
        "sub_pages": [],
        "estimated_word_count": 1980
      }
    },
    {
      "parent_topic": "cat bowl set",
      "keywords": [
        "cat bowl set"
      ],
      "cluster_score": 0.5,
      "category_type": "topic",
      "keyword_count": 1,
      "category": "Semantic Topics",
      "priority": 2,
      "content_recommendations": {
        "pillar_title": "Complete Guide to cat bowl set",
        "pillar_description": "Comprehensive guide to cat bowl set. Learn everything about cat bowl set including best practices, expert tips, and actionable strategies.",
        "pillar_url": "/complete-guide-to-cat-bowl-set",
        "sub_pages": [],
        "estimated_word_count": 1980
      }
    },
    {
      "parent_topic": "cat bowl bed",
      "keywords": [
        "cat bowl bed"
      ],
      "cluster_score": 0.5,
      "category_type": "topic",
      "keyword_count": 1,
      "category": "Semantic Topics",
      "priority": 2,
      "content_recommendations": {
        "pillar_title": "Complete Guide to cat bowl bed",
        "pillar_description": "Comprehensive guide to cat bowl bed. Learn everything about cat bowl bed including best practices, expert tips, and actionable strategies.",
        "pillar_url": "/complete-guide-to-cat-bowl-bed",
        "sub_pages": [],
        "estimated_word_count": 1980
      }
    },
    {
      "parent_topic": "cat bowls near me",
      "keywords": [
        "cat bowls near me"
      ],
      "cluster_score": 0.5,
      "category_type": "topic",
      "keyword_count": 1,
      "category": "Semantic Topics",
      "priority": 2,
      "content_recommendations": {
        "pillar_title": "Complete Guide to cat bowls near me",
        "pillar_description": "Comprehensive guide to cat bowls near me. Learn everything about cat bowls near me including best practices, expert tips, and actionable strategies.",
        "pillar_url": "/complete-guide-to-cat-bowls-near-me",
        "sub_pages": [],
        "estimated_word_count": 1980
      }
    },
    {
      "parent_topic": "cat bowling ball",
      "keywords": [
        "cat bowling ball"
      ],
      "cluster_score": 0.5,
      "category_type": "topic",
      "keyword_count": 1,
      "category": "Semantic Topics",
      "priority": 2,
      "content_recommendations": {
        "pillar_title": "Complete Guide to cat bowling ball",
        "pillar_description": "Comprehensive guide to cat bowling ball. Learn everything about cat bowling ball including best practices, expert tips, and actionable strategies.",
        "pillar_url": "/complete-guide-to-cat-bowling-ball",
        "sub_pages": [],
        "estimated_word_count": 1980
      }
    },
    {
      "parent_topic": "cat bowls walmart",
      "keywords": [
        "cat bowls walmart"
      ],
      "cluster_score": 0.5,
      "category_type": "topic",
      "keyword_count": 1,
      "category": "Semantic Topics",
      "priority": 2,
      "content_recommendations": {
        "pillar_title": "Complete Guide to cat bowls walmart",
        "pillar_description": "Comprehensive guide to cat bowls walmart. Learn everything about cat bowls walmart including best practices, expert tips, and actionable strategies.",
        "pillar_url": "/complete-guide-to-cat-bowls-walmart",
        "sub_pages": [],
        "estimated_word_count": 1980
      }
    }
  ],
  "cluster_summary": {
    "total_keywords": 14,
    "cluster_count": 14,
    "unclustered_count": 0
  },
  "location": {
    "used": "United States",
    "detected_from_ip": false,
    "specified": false
  },
  "discovery": {
    "matching_terms": [
      {
        "keyword": "cat bowl",
        "search_volume": 8100,
        "keyword_difficulty": 0,
        "cpc": 0.96,
        "competition": 1,
        "parent_topic": null,
        "intent": "transactional"
      },
      {
        "keyword": "cat bowls",
        "search_volume": 8100,
        "keyword_difficulty": 0,
        "cpc": 0.96,
        "competition": 1,
        "parent_topic": null,
        "intent": "transactional"
      },
      {
        "keyword": "stainless steel cat bowls",
        "search_volume": 5400,
        "keyword_difficulty": 0,
        "cpc": 1.07,
        "competition": 0.74,
        "parent_topic": null,
        "intent": "transactional"
      },
      {
        "keyword": "cat bowls elevated",
        "search_volume": 4400,
        "keyword_difficulty": 0,
        "cpc": 1.01,
        "competition": 1,
        "parent_topic": null,
        "intent": "transactional"
      },
      {
        "keyword": "elevated cat bowls",
        "search_volume": 4400,
        "keyword_difficulty": 0,
        "cpc": 1.03,
        "competition": 1,
        "parent_topic": null,
        "intent": "transactional"
      },
      {
        "keyword": "elevated cat bowl",
        "search_volume": 4400,
        "keyword_difficulty": 0,
        "cpc": 1.03,
        "competition": 1,
        "parent_topic": null,
        "intent": "transactional"
      },
      {
        "keyword": "cat bowl ceramic",
        "search_volume": 2900,
        "keyword_difficulty": 0,
        "cpc": 1.01,
        "competition": 1,
        "parent_topic": null,
        "intent": "transactional"
      },
      {
        "keyword": "ceramic cat bowls",
        "search_volume": 2900,
        "keyword_difficulty": 0,
        "cpc": 1.01,
        "competition": 1,
        "parent_topic": null,
        "intent": "transactional"
      },
      {
        "keyword": "elevated cat bowls ceramic",
        "search_volume": 1300,
        "keyword_difficulty": 0,
        "cpc": 1.06,
        "competition": 1,
        "parent_topic": null,
        "intent": "transactional"
      },
      {
        "keyword": "cat bowls with stand",
        "search_volume": 880,
        "keyword_difficulty": 0,
        "cpc": 0.89,
        "competition": 1,
        "parent_topic": null,
        "intent": "transactional"
      },
      {
        "keyword": "best cat bowl",
        "search_volume": 880,
        "keyword_difficulty": 0,
        "cpc": 1.25,
        "competition": 1,
        "parent_topic": null,
        "intent": "transactional"
      },
      {
        "keyword": "cat food bowl ceramic",
        "search_volume": 880,
        "keyword_difficulty": 0,
        "cpc": 0.96,
        "competition": 1,
        "parent_topic": null,
        "intent": "transactional"
      },
      {
        "keyword": "cat bowl amazon",
        "search_volume": 260,
        "keyword_difficulty": 0,
        "cpc": 0.55,
        "competition": 0.95,
        "parent_topic": null,
        "intent": "transactional"
      },
      {
        "keyword": "cat bowls metal",
        "search_volume": 260,
        "keyword_difficulty": 0,
        "cpc": 0.97,
        "competition": 1,
        "parent_topic": null,
        "intent": "transactional"
      },
      {
        "keyword": "elevated cat bowls good or bad",
        "search_volume": 210,
        "keyword_difficulty": 0,
        "cpc": 0.8,
        "competition": 1,
        "parent_topic": null,
        "intent": "transactional"
      },
      {
        "keyword": "best cat bowls for whisker fatigue",
        "search_volume": 210,
        "keyword_difficulty": 0,
        "cpc": 1.16,
        "competition": 1,
        "parent_topic": null,
        "intent": "transactional"
      },
      {
        "keyword": "cat bowl set",
        "search_volume": 170,
        "keyword_difficulty": 0,
        "cpc": 0.63,
        "competition": 1,
        "parent_topic": null,
        "intent": "transactional"
      },
      {
        "keyword": "ceramic cat bowl set",
        "search_volume": 140,
        "keyword_difficulty": 0,
        "cpc": 0.68,
        "competition": 1,
        "parent_topic": null,
        "intent": "transactional"
      },
      {
        "keyword": "best cat bowl material",
        "search_volume": 140,
        "keyword_difficulty": 0,
        "cpc": 0.73,
        "competition": 1,
        "parent_topic": null,
        "intent": "transactional"
      },
      {
        "keyword": "stainless steel cat bowls with stand",
        "search_volume": 140,
        "keyword_difficulty": 0,
        "cpc": 0.93,
        "competition": 1,
        "parent_topic": null,
        "intent": "transactional"
      },
      {
        "keyword": "cat bowl stand without bowls",
        "search_volume": 90,
        "keyword_difficulty": 0,
        "cpc": 0.68,
        "competition": 1,
        "parent_topic": null,
        "intent": "transactional"
      },
      {
        "keyword": "best cat bowls for wet food",
        "search_volume": 90,
        "keyword_difficulty": 0,
        "cpc": 1.29,
        "competition": 1,
        "parent_topic": null,
        "intent": "transactional"
      },
      {
        "keyword": "raised stainless steel cat bowls",
        "search_volume": 90,
        "keyword_difficulty": 0,
        "cpc": 0.88,
        "competition": 1,
        "parent_topic": null,
        "intent": "transactional"
      },
      {
        "keyword": "large cat bowl",
        "search_volume": 70,
        "keyword_difficulty": 0,
        "cpc": 0.62,
        "competition": 1,
        "parent_topic": null,
        "intent": "transactional"
      },
      {
        "keyword": "elevated cat bowl set",
        "search_volume": 70,
        "keyword_difficulty": 0,
        "cpc": 0.83,
        "competition": 1,
        "parent_topic": null,
        "intent": "transactional"
      },
      {
        "keyword": "elevated shallow cat bowl",
        "search_volume": 70,
        "keyword_difficulty": 0,
        "cpc": 0.89,
        "competition": 1,
        "parent_topic": null,
        "intent": "transactional"
      },
      {
        "keyword": "wood cat bowl stand",
        "search_volume": 70,
        "keyword_difficulty": 0,
        "cpc": 0.75,
        "competition": 1,
        "parent_topic": null,
        "intent": "transactional"
      },
      {
        "keyword": "cute cat bowl set",
        "search_volume": 50,
        "keyword_difficulty": 0,
        "cpc": 1.09,
        "competition": 1,
        "parent_topic": null,
        "intent": "transactional"
      },
      {
        "keyword": "amazon elevated cat bowls",
        "search_volume": 50,
        "keyword_difficulty": 0,
        "cpc": 0.51,
        "competition": 0.99,
        "parent_topic": null,
        "intent": "transactional"
      },
      {
        "keyword": "big cats bowls menu",
        "search_volume": 50,
        "keyword_difficulty": 0,
        "cpc": 0.0,
        "competition": 0.0,
        "parent_topic": null,
        "intent": "informational"
      },
      {
        "keyword": "elevated tilted cat bowls ceramic",
        "search_volume": 50,
        "keyword_difficulty": 0,
        "cpc": 0.71,
        "competition": 1,
        "parent_topic": null,
        "intent": "transactional"
      },
      {
        "keyword": "stainless steel cat bowls made in usa",
        "search_volume": 50,
        "keyword_difficulty": 0,
        "cpc": 1.7,
        "competition": 1,
        "parent_topic": null,
        "intent": "transactional"
      },
      {
        "keyword": "best cat bowls for water",
        "search_volume": 40,
        "keyword_difficulty": 0,
        "cpc": 1.45,
        "competition": 1,
        "parent_topic": null,
        "intent": "transactional"
      },
      {
        "keyword": "stainless steel cat bowls whisker fatigue",
        "search_volume": 40,
        "keyword_difficulty": 0,
        "cpc": 0.76,
        "competition": 1,
        "parent_topic": null,
        "intent": "transactional"
      },
      {
        "keyword": "cat food and water bowl set",
        "search_volume": 30,
        "keyword_difficulty": 0,
        "cpc": 1.64,
        "competition": 1,
        "parent_topic": null,
        "intent": "transactional"
      },
      {
        "keyword": "best cat bowls for messy eaters",
        "search_volume": 30,
        "keyword_difficulty": 0,
        "cpc": 0.71,
        "competition": 1,
        "parent_topic": null,
        "intent": "transactional"
      },
      {
        "keyword": "ceramic cat bowl amazon",
        "search_volume": 30,
        "keyword_difficulty": 0,
        "cpc": 0.81,
        "competition": 0.89,
        "parent_topic": null,
        "intent": "transactional"
      },
      {
        "keyword": "raised ceramic cat food bowls",
        "search_volume": 20,
        "keyword_difficulty": 0,
        "cpc": 0.51,
        "competition": 1,
        "parent_topic": null,
        "intent": "transactional"
      },
      {
        "keyword": "shallow ceramic cat dish",
        "search_volume": 10,
        "keyword_difficulty": 0,
        "cpc": 0.19,
        "competition": 1,
        "parent_topic": null,
        "intent": "transactional"
      },
      {
        "keyword": "cat bowls elevated whisker fatigue",
        "search_volume": 10,
        "keyword_difficulty": 0,
        "cpc": 0.45,
        "competition": 1,
        "parent_topic": null,
        "intent": "transactional"
      },
      {
        "keyword": "best cat bowl reddit",
        "search_volume": 10,
        "keyword_difficulty": 0,
        "cpc": 0.34,
        "competition": 0.88,
        "parent_topic": null,
        "intent": "informational"
      }
    ],
    "questions": [],
    "related_terms": []
  },
  "serp_analysis": {
    "keyword": "Cat bowl",
    "organic_results": [],
    "people_also_ask": [],
    "featured_snippet": null,
    "video_results": [],
    "image_results": [],
    "related_searches": [],
    "top_domains": [],
    "competition_level": "medium",
    "content_gaps": [],
    "serp_features": {
      "has_featured_snippet": false,
      "has_people_also_ask": false,
      "has_videos": false,
      "has_images": false
    }
  }
}